cohere_compass/__init__.py
cohere_compass/clients/__init__.py
cohere_compass/clients/access_control.py
cohere_compass/clients/compass.py
cohere_compass/clients/compass_async.py
cohere_compass/clients/parser.py
cohere_compass/clients/parser_async.py
cohere_compass/constants.py
cohere_compass/exceptions.py
cohere_compass/models/__init__.py
cohere_compass/models/access_control.py
cohere_compass/models/config.py
cohere_compass/models/datasources.py
cohere_compass/models/documents.py
cohere_compass/models/indexes.py
cohere_compass/models/search.py
cohere_compass/py.typed
cohere_compass/utils/__init__.py
cohere_compass/utils/asyn.py
cohere_compass/utils/documents.py
cohere_compass/utils/fs.py
cohere_compass/utils/iter.py
cohere_compass/utils/retry.py
cohere_compass_sdk-2.3.3.dist-info/LICENSE
cohere_compass_sdk-2.3.3.dist-info/METADATA
cohere_compass_sdk-2.3.3.dist-info/WHEEL
cohere_compass_sdk-2.3.3.dist-info/RECORD
