Metadata-Version: 2.1
Name: cohere-compass-sdk
Version: 2.3.3
Summary: Cohere Compass SDK
Requires-Python: >=3.11,<4.0
Classifier: Programming Language :: Python :: 3
Classifier: Programming Language :: Python :: 3.11
Requires-Dist: fsspec (>=2025.9.0,<2026.0.0)
Requires-Dist: httpx (>=0.28.1,<0.29.0)
Requires-Dist: joblib (>=1.5.2,<2.0.0)
Requires-Dist: pydantic (>=2.11.9,<3.0.0)
Requires-Dist: tenacity (>=9.1.2,<10.0.0)
